tolerantjson/__init__.py
tolerantjson/parser.py
tolerantjson-1.0.0.dist-info/LICENSE
tolerantjson-1.0.0.dist-info/METADATA
tolerantjson-1.0.0.dist-info/WHEEL
tolerantjson-1.0.0.dist-info/top_level.txt
tolerantjson-1.0.0.dist-info/RECORD
