Metadata-Version: 2.1
Name: tolerantjson
Version: 1.0.0
Summary: A JSON parser that tolerates common syntax errors.
Author-email: Nurettin Abacı <abacinurettin@gmail.com>
License: The MIT License (MIT)
Project-URL: Homepage, https://github.com/nurettn/tolerantjson
Project-URL: Repository, https://github.com/nurettn/tolerantjson
Keywords: json,parser,tolerant,error-handling
Classifier: License :: OSI Approved :: MIT License
Classifier: Programming Language :: Python
Classifier: Programming Language :: Python :: 3
Classifier: Operating System :: OS Independent
Classifier: Topic :: Software Development :: Libraries :: Python Modules
Classifier: Topic :: Utilities
Requires-Python: >=3.6
License-File: LICENSE
Provides-Extra: dev
Requires-Dist: black ; extra == 'dev'
Requires-Dist: bumpver ; extra == 'dev'
Requires-Dist: isort ; extra == 'dev'
